amicleaner/__init__.py
amicleaner/cli.py
amicleaner/core.py
amicleaner/fetch.py
amicleaner/utils.py
amicleaner/resources/__init__.py
amicleaner/resources/config.py
amicleaner/resources/models.py
aws_amicleaner-0.2.2.dist-info/DESCRIPTION.rst
aws_amicleaner-0.2.2.dist-info/METADATA
aws_amicleaner-0.2.2.dist-info/RECORD
aws_amicleaner-0.2.2.dist-info/WHEEL
aws_amicleaner-0.2.2.dist-info/entry_points.txt
aws_amicleaner-0.2.2.dist-info/metadata.json
aws_amicleaner-0.2.2.dist-info/top_level.txt
