Metadata-Version: 2.0
Name: aws-amicleaner
Version: 0.2.2
Summary: Cleanup tool for AWS AMIs and snapshots
Home-page: https://github.com/bonclay7/aws-amicleaner/
Author: Guy Rodrigue Koffi
Author-email: koffirodrigue@gmail.com
License: MIT
Platform: UNKNOWN
Classifier: Development Status :: 5 - Production/Stable
Classifier: Environment :: Console
Classifier: Intended Audience :: Developers
Classifier: Intended Audience :: System Administrators
Classifier: Intended Audience :: Information Technology
Classifier: License :: OSI Approved :: MIT License
Classifier: Operating System :: OS Independent
Classifier: Programming Language :: Python
Classifier: Programming Language :: Python :: 2
Classifier: Programming Language :: Python :: 2.7
Classifier: Programming Language :: Python :: 3
Classifier: Programming Language :: Python :: 3.3
Classifier: Programming Language :: Python :: 3.4
Classifier: Programming Language :: Python :: 3.5
Classifier: Programming Language :: Python :: 3.6
Classifier: Topic :: Software Development
Classifier: Topic :: Software Development :: Libraries :: Python Modules
Requires-Dist: awscli
Requires-Dist: argparse
Requires-Dist: boto
Requires-Dist: boto3
Requires-Dist: prettytable
Requires-Dist: blessings
